[
  {
    "title": "Assorted Brake Bleed Screws",
    "code": "ATM034",
    "priceInc": "57.68",
    "priceEx": "",
    "packSize": "1",
    "inStock": false,
    "imageUrl": "https://shop.autogem.co.uk/userfiles/images/products/188x188/ATM034.jpg",
    "url": "https://shop.autogem.co.uk/product/brake-fittings-bb02/assorted-brake-bleed-screws-atm034",
    "equivalentTo": "",
    "description": "Assorted Brake Pipe Fittings & Brake B..."
  },
  {
    "title": "Assorted Brake Pipe Fittings",
    "code": "ATM033",
    "priceInc": "36.52",
    "priceEx": "",
    "packSize": "1",
    "inStock": false,
    "imageUrl": "https://shop.autogem.co.uk/userfiles/images/products/188x188/ATM033.jpg",
    "url": "https://shop.autogem.co.uk/product/brake-fittings-bb02/assorted-brake-pipe-fittings-atm033",
    "equivalentTo": "",
    "description": "Assorted Grease Nipples"
  },
  {
    "title": "Assorted Brake Pipe Fittings & Brake B...",
    "code": "AT79",
    "priceInc": "38.36",
    "priceEx": "",
    "packSize": "1",
    "inStock": false,
    "imageUrl": "https://shop.autogem.co.uk/userfiles/images/products/188x188/AT79.jpg",
    "url": "https://shop.autogem.co.uk/product/brake-fittings-bb02/assorted-brake-pipe-fittings-brake-bleed-screws-at79",
    "equivalentTo": "",
    "description": "Assorted Grease Nipples"
  },
  {
    "title": "Assorted Grease Nipples",
    "code": "ATM065",
    "priceInc": "55.88",
    "priceEx": "",
    "packSize": "125pcs",
    "inStock": false,
    "imageUrl": "https://shop.autogem.co.uk/userfiles/images/products/188x188/ATM065.jpg",
    "url": "https://shop.autogem.co.uk/product/brake-fittings-bb02/assorted-grease-nipples-atm065",
    "equivalentTo": "",
    "description": "Assorted Grease Nipples"
  },
  {
    "title": "Assorted Grease Nipples",
    "code": "ATM066",
    "priceInc": "52.43",
    "priceEx": "",
    "packSize": "150pcs",
    "inStock": false,
    "imageUrl": "https://shop.autogem.co.uk/userfiles/images/products/188x188/ATM066.jpg",
    "url": "https://shop.autogem.co.uk/product/brake-fittings-bb02/assorted-grease-nipples-atm066",
    "equivalentTo": "",
    "description": "Assorted Grease Nipples"
  }
]