[
  {
    "title": "19mm x 20m PVC Tape - Black",
    "code": "ADH111",
    "priceInc": "8.48",
    "priceEx": "",
    "packSize": "2",
    "inStock": false,
    "imageUrl": "https://shop.autogem.co.uk/userfiles/images/products/188x188/ADH111.jpg",
    "url": "https://shop.autogem.co.uk/product/tapes-insulation-ba05/19mm-x-20m-pvc-tape-black-adh111",
    "equivalentTo": "",
    "description": "19mm x 20m PVC Tape - Blue"
  },
  {
    "title": "19mm x 20m PVC Tape - Blue",
    "code": "ADH133",
    "priceInc": "9.10",
    "priceEx": "",
    "packSize": "10",
    "inStock": false,
    "imageUrl": "https://shop.autogem.co.uk/userfiles/images/products/188x188/ADH133.jpg",
    "url": "https://shop.autogem.co.uk/product/tapes-insulation-ba05/19mm-x-20m-pvc-tape-blue-adh133",
    "equivalentTo": "",
    "description": "19mm x 20m PVC Tape - Blue"
  },
  {
    "title": "19mm x 20m PVC Tape - Green",
    "code": "ADH135",
    "priceInc": "8.94",
    "priceEx": "",
    "packSize": "10",
    "inStock": false,
    "imageUrl": "https://shop.autogem.co.uk/userfiles/images/products/188x188/ADH135.jpg",
    "url": "https://shop.autogem.co.uk/product/tapes-insulation-ba05/19mm-x-20m-pvc-tape-green-adh135",
    "equivalentTo": "",
    "description": "19mm x 20m PVC Tape - Blue"
  },
  {
    "title": "19mm x 20m PVC Tape - Red",
    "code": "ADH113",
    "priceInc": "8.94",
    "priceEx": "",
    "packSize": "10",
    "inStock": false,
    "imageUrl": "https://shop.autogem.co.uk/userfiles/images/products/188x188/ADH113.jpg",
    "url": "https://shop.autogem.co.uk/product/tapes-insulation-ba05/19mm-x-20m-pvc-tape-red-adh113",
    "equivalentTo": "",
    "description": "19mm x 20m PVC Tape - White"
  },
  {
    "title": "19mm x 20m PVC Tape - White",
    "code": "ADH132",
    "priceInc": "8.94",
    "priceEx": "",
    "packSize": "10",
    "inStock": false,
    "imageUrl": "https://shop.autogem.co.uk/userfiles/images/products/188x188/ADH132.jpg",
    "url": "https://shop.autogem.co.uk/product/tapes-insulation-ba05/19mm-x-20m-pvc-tape-white-adh132",
    "equivalentTo": "",
    "description": "19mm x 20m PVC Tape - Blue"
  },
  {
    "title": "19mm x 20m PVC Tape - Yellow",
    "code": "ADH138",
    "priceInc": "7.21",
    "priceEx": "",
    "packSize": "10",
    "inStock": false,
    "imageUrl": "https://shop.autogem.co.uk/userfiles/images/products/188x188/ADH138.jpg",
    "url": "https://shop.autogem.co.uk/product/tapes-insulation-ba05/19mm-x-20m-pvc-tape-yellow-adh138",
    "equivalentTo": "",
    "description": "19mm x 20m PVC Tape - Black"
  },
  {
    "title": "19mm x 20m PVC Tape - Yellow/ Green",
    "code": "ADH136",
    "priceInc": "8.94",
    "priceEx": "",
    "packSize": "10",
    "inStock": false,
    "imageUrl": "https://shop.autogem.co.uk/userfiles/images/products/188x188/ADH136.jpg",
    "url": "https://shop.autogem.co.uk/product/tapes-insulation-ba05/19mm-x-20m-pvc-tape-yellow-green-adh136",
    "equivalentTo": "",
    "description": "19mm x 20m PVC Tape - Green"
  }
]